Topsis_Maanya_102066004/__init__.py
Topsis_Maanya_102066004/topsis.py
Topsis_Manya_102066004-1.3.1.dist-info/LICENSE.txt
Topsis_Manya_102066004-1.3.1.dist-info/METADATA
Topsis_Manya_102066004-1.3.1.dist-info/WHEEL
Topsis_Manya_102066004-1.3.1.dist-info/top_level.txt
Topsis_Manya_102066004-1.3.1.dist-info/RECORD
